appdynamics_proxysupport/COPYRIGHT
appdynamics_proxysupport/LICENSE
appdynamics_proxysupport/README
appdynamics_proxysupport/THIRDPARTYLICENSEREADME-JAVAFX.txt
appdynamics_proxysupport/THIRDPARTYLICENSEREADME.txt
appdynamics_proxysupport/Welcome.html
appdynamics_proxysupport/__init__.py
appdynamics_proxysupport/release
appdynamics_proxysupport/bin/java
appdynamics_proxysupport/bin/jjs
appdynamics_proxysupport/bin/keytool
appdynamics_proxysupport/bin/orbd
appdynamics_proxysupport/bin/pack200
appdynamics_proxysupport/bin/policytool
appdynamics_proxysupport/bin/rmid
appdynamics_proxysupport/bin/rmiregistry
appdynamics_proxysupport/bin/servertool
appdynamics_proxysupport/bin/tnameserv
appdynamics_proxysupport/bin/unpack200
appdynamics_proxysupport/lib/calendars.properties
appdynamics_proxysupport/lib/charsets.jar
appdynamics_proxysupport/lib/classlist
appdynamics_proxysupport/lib/content-types.properties
appdynamics_proxysupport/lib/currency.data
appdynamics_proxysupport/lib/flavormap.properties
appdynamics_proxysupport/lib/fontconfig.bfc
appdynamics_proxysupport/lib/fontconfig.properties.src
appdynamics_proxysupport/lib/hijrah-config-umalqura.properties
appdynamics_proxysupport/lib/javafx.properties
appdynamics_proxysupport/lib/jce.jar
appdynamics_proxysupport/lib/jfr.jar
appdynamics_proxysupport/lib/jfxswt.jar
appdynamics_proxysupport/lib/jspawnhelper
appdynamics_proxysupport/lib/jsse.jar
appdynamics_proxysupport/lib/jvm.cfg
appdynamics_proxysupport/lib/jvm.hprof.txt
appdynamics_proxysupport/lib/libAppleScriptEngine.dylib
appdynamics_proxysupport/lib/libattach.dylib
appdynamics_proxysupport/lib/libawt.dylib
appdynamics_proxysupport/lib/libawt_lwawt.dylib
appdynamics_proxysupport/lib/libbci.dylib
appdynamics_proxysupport/lib/libdcpr.dylib
appdynamics_proxysupport/lib/libdecora_sse.dylib
appdynamics_proxysupport/lib/libdt_socket.dylib
appdynamics_proxysupport/lib/libfontmanager.dylib
appdynamics_proxysupport_osx_x64-1.8.0.212.1.dist-info/DESCRIPTION.rst
appdynamics_proxysupport_osx_x64-1.8.0.212.1.dist-info/METADATA
appdynamics_proxysupport_osx_x64-1.8.0.212.1.dist-info/RECORD
appdynamics_proxysupport_osx_x64-1.8.0.212.1.dist-info/WHEEL
appdynamics_proxysupport_osx_x64-1.8.0.212.1.dist-info/metadata.json
appdynamics_proxysupport_osx_x64-1.8.0.212.1.dist-info/top_level.txt
