Metadata-Version: 2.0
Name: appdynamics-proxysupport-osx-x64
Version: 1.8.0.212.1
Summary: Proxysupport for AppDynamics Python agent
Home-page: http://www.appdynamics.com
Author: AppDynamics
Author-email: support@appdynamics.com
License: Proprietary
Platform: UNKNOWN
